stronger/__init__.py
stronger-0.0.0.dist-info/LICENSE
stronger-0.0.0.dist-info/WHEEL
stronger-0.0.0.dist-info/METADATA
stronger-0.0.0.dist-info/RECORD
