Metadata-Version: 2.1
Name: stronger
Version: 0.0.0
Summary: Stronger string processing with stringers.
Author-email: Blake Naccarato <blake.naccarato@gmail.com>
Requires-Python: >=3.11
Classifier: License :: OSI Approved :: MIT License
Project-URL: Changes, https://blakeNaccarato.github.io/stronger/changelog.html
Project-URL: Docs, https://blakeNaccarato.github.io/stronger
Project-URL: Home, https://github.com/blakeNaccarato/stronger
Project-URL: Tracker, https://github.com/blakeNaccarato/stronger/issues
